gridnetwork/__init__.py
gridnetwork/codes.py
gridnetwork/events/__init__.py
gridnetwork/events/network.py
gridnetwork/events/socket_handler.py
gridnetwork/routes/__init__.py
gridnetwork/routes/dataset.py
gridnetwork/routes/general.py
gridnetwork/routes/models.py
gridnetwork/routes/nodes.py
gridnetwork/workers/__init__.py
gridnetwork/workers/worker.py
test/__init__.py
test/conftest.py
openmined.gridnetwork-0.1.0.dist-info/LICENSE
openmined.gridnetwork-0.1.0.dist-info/METADATA
openmined.gridnetwork-0.1.0.dist-info/WHEEL
openmined.gridnetwork-0.1.0.dist-info/entry_points.txt
openmined.gridnetwork-0.1.0.dist-info/top_level.txt
openmined.gridnetwork-0.1.0.dist-info/RECORD
